{
  "sections": {
    "main": {
      "type": "product",
      "blocks": {
        "title": {
          "type": "title",
          "settings": {
            "product_show_vendor": false,
            "show_rating": false,
            "show_rating_count": false
          }
        },
        "form": {
          "type": "form",
          "settings": {
            "variant_form": "auto",
            "show_quantity": true,
            "enable_payment_button": true,
            "subscriptions_enable_selectors": false,
            "show_remaining": true,
            "show_remaining_style": "low",
            "countdown": 10,
            "info_page": ""
          }
        },
        "pickup": {
          "type": "pickup",
          "disabled": true,
          "settings": {
          }
        },
        "description": {
          "type": "description",
          "settings": {
            "read_more": true,
            "enable_description": true,
            "icon_description": "",
            "style": "accordions",
            "title_1": "",
            "icon_name_1": "",
            "raw_content_1": "<p><\/p><p><\/p>",
            "title_2": "Nails Information",
            "icon_name_2": "",
            "raw_content_2": "<p>Nails Shape : {{ product.metafields.custom.nails_shape.value }}<\/p><p>Nails Length :  {{ product.metafields.custom.nails_length | metafield_tag }}<\/p><p>Nails Finish :  {{ product.metafields.custom.finish.value }}<\/p><p><\/p>",
            "title_3": "",
            "icon_name_3": "",
            "raw_content_3": "",
            "title_4": "",
            "icon_name_4": "",
            "raw_content_4": "",
            "title_5": "",
            "icon_name_5": "",
            "raw_content_5": ""
          }
        },
        "sharing": {
          "type": "sharing",
          "settings": {
          }
        }
      },
      "block_order": [
        "title",
        "form",
        "pickup",
        "description",
        "sharing"
      ],
      "settings": {
        "image_width": "wide",
        "align": "left",
        "product_breadcrumbs": true,
        "enable_video_looping": true,
        "zoom_enable": true,
        "bg": "palette--light bg--neutral"
      }
    },
    "judgeme_section_review_widget_f2b7": {
      "type": "apps",
      "blocks": {
        "judgeme_review_widget_a00f1f26": {
          "type": "shopify:\/\/apps\/judge-me-product-reviews\/blocks\/review_widget\/61ccd3b1-a9f2-4160-9fe9-4fec8413e5d8",
          "settings": {
          }
        }
      },
      "block_order": [
        "judgeme_review_widget_a00f1f26"
      ],
      "settings": {
        "width": "wrapper",
        "height": "margin--medium",
        "text_color": "text--neutral",
        "bg": "palette--light bg--neutral"
      }
    },
    "image-with-text": {
      "type": "section-double",
      "disabled": true,
      "blocks": {
        "image": {
          "type": "image",
          "settings": {
            "bg_position": "center-center",
            "overlay_opacity": 15,
            "overlay_color": "#000000",
            "kicker": "",
            "title": "",
            "richtext": "",
            "text_align": "align--middle-center",
            "text_color": "text--white",
            "link_text": "",
            "link": "",
            "button_color": "btn--white",
            "button_style": "btn uppercase"
          }
        },
        "text": {
          "type": "text",
          "settings": {
            "kicker": "Image with text",
            "title": "",
            "text": "<p>Use this text to share information about your brand with your customers. Describe a product, share announcements, or welcome customers to your store.<\/p>",
            "text_size": 2,
            "text_columns": 1,
            "align_text": "text-left",
            "button_text": "",
            "button_url": "",
            "button_color": "btn--neutral",
            "button_style": "caps--link",
            "text_color": "text--neutral",
            "bg_color": "#ffffff"
          }
        }
      },
      "block_order": [
        "image",
        "text"
      ],
      "settings": {
        "height": "use_screen_one_half",
        "padding": true,
        "borders": false,
        "wrapper": true
      }
    },
    "reviews": {
      "type": "reviews",
      "settings": {
        "product_reviews_enable": true,
        "bg": "palette--light bg--accent"
      }
    },
    "related": {
      "type": "related",
      "settings": {
        "heading": "You might also like",
        "bg": "palette--light bg--neutral",
        "grid": 4,
        "related_products_enable": true,
        "limit": 6,
        "product_recommendations_heading": "Related products",
        "show_recently_viewed": true,
        "product_recently_limit": 6,
        "product_recently_minimum": 4,
        "product_recently_heading": "Recently viewed"
      }
    }
  },
  "order": [
    "main",
    "judgeme_section_review_widget_f2b7",
    "image-with-text",
    "reviews",
    "related"
  ]
}